genepro/__init__.py
genepro/evo.py
genepro/node.py
genepro/node_impl.py
genepro/scikit.py
genepro/selection.py
genepro/util.py
genepro/variation.py
genepro-0.1.3.dist-info/LICENSE
genepro-0.1.3.dist-info/METADATA
genepro-0.1.3.dist-info/WHEEL
genepro-0.1.3.dist-info/top_level.txt
genepro-0.1.3.dist-info/RECORD
