Metadata-Version: 2.1
Name: genepro
Version: 0.1.3
Home-page: https://github.com/marcovirgolin/genepro
Author: Marco Virgolin
Author-email: marco.virgolin@gmail.com
Classifier: Programming Language :: Python :: 3
Classifier: License :: OSI Approved :: MIT License
Classifier: Operating System :: OS Independent
Requires-Python: >=3.7
License-File: LICENSE
Requires-Dist: numpy >=1.22.2
Requires-Dist: scikit-learn >=1.0.2
Requires-Dist: joblib >=1.1.0
